dokitchensink/__init__.py
dokitchensink/apiwrapper.py
dokitchensink/cli_interface.py
dokitchensink-0.2.0.dist-info/entry_points.txt
dokitchensink-0.2.0.dist-info/LICENSE
dokitchensink-0.2.0.dist-info/WHEEL
dokitchensink-0.2.0.dist-info/METADATA
dokitchensink-0.2.0.dist-info/RECORD
