Metadata-Version: 2.1
Name: dokitchensink
Version: 0.2.0
Summary: Thin wrapper for python-digitalocean, mostly to automate DNS record creation after droplet creation
Home-page: https://github.com/avollmerhaus/dokitchensink
Author: Aljoscha Vollmerhaus
Author-email: git@aljoscha.vollmerhaus.net
Requires-Python: >=3.8,<4.0
Classifier: Programming Language :: Python :: 3
Classifier: Programming Language :: Python :: 3.8
Classifier: Programming Language :: Python :: 3.9
Requires-Dist: python-digitalocean (>=1.15.0,<2.0.0)
